{
    "career": [
        {
            "position": "Sakkunnig vid utredning för organisation av arméns och marinens flyg- och ballongvapen samt Sveriges försvar mot anfall från luften med mera",
            "start_year": 1917,
            "end_year": 1921,
            "organization": null,
            "location": null,
            "country_code": null
        },
        {
            "position": "Vid internationella förhandlingar angående avlägsnande eller förstörelse av å Åland utförda befästningar och andra militära anläggningar",
            "start_year": 1918,
            "end_year": null,
            "organization": null,
            "location": {
                "name": "Åland",
                "latitude": 60.1785247,
                "longitude": 19.9156105,
                "formatted_address": "Åland Islands"
            },
            "country_code": null
        },
        {
            "position": "Inom civil departementet biträde med utarbetande av förslag till lufttrafikförordning för Sverige",
            "start_year": 1918,
            "end_year": null,
            "organization": "Civil departementet",
            "location": null,
            "country_code": "SWE"
        }
    ],
    "person": {
        "first_name": "Mia",
        "last_name": "Löfqvist",
        "middle_name": null,
        "gender": "Female",
        "birth_date": null,
        "birth_place": null,
        "occupation": null,
        "parents": [
            {
                "first_name": "And.",
                "last_name": "Löfqvist",
                "middle_name": null,
                "gender": "Male",
                "occupation": {
                    "occupation": "Direktör",
                    "occupation_english": "Director",
                    "hisco_code_swedish": "21110.0",
                    "hisco_description_swedish": "General Manager",
                    "hisco_code_english": "21000.0",
                    "hisco_description_english": "Manager, Specialisation Unknown"
                }
            },
            {
                "first_name": "Agnes",
                "last_name": "Schiffter",
                "middle_name": null,
                "gender": "Female",
                "occupation": null
            }
        ]
    },
    "academic_positions": null,
    "achievements": null,
    "awards": null,
    "board_memberships": null,
    "committee_memberships": null,
    "community_involvement": null,
    "current_location": null,
    "education": null,
    "family": {
        "spouse": null,
        "marriage_year": "1896",
        "divorce_year": null,
        "children": null
    },
    "hobbies": null,
    "honorary_titles": null,
    "honors": null,
    "languages_spoken": null,
    "leadership_roles": null,
    "military_service": null,
    "political_positions": null,
    "publications": null,
    "travels": [
        {
            "country": {
                "name": "Sachsen",
                "latitude": 51.1045407,
                "longitude": 13.2017384,
                "formatted_address": "Saxony, Germany"
            },
            "country_code": "DEU",
            "year": "1916"
        },
        {
            "country": {
                "name": "Tyskland",
                "latitude": 51.165691,
                "longitude": 10.451526,
                "formatted_address": "Germany"
            },
            "country_code": "DEU",
            "year": "1916"
        }
    ]
}