{
    "career": [
        {
            "position": "lektor",
            "start_year": 1937,
            "end_year": 1951,
            "organization": "Landskrona hal",
            "location": {
                "name": "Landskrona",
                "latitude": 55.8703477,
                "longitude": 12.8300802,
                "formatted_address": "Landskrona, Sweden"
            },
            "country_code": null
        },
        {
            "position": "professor",
            "start_year": 1951,
            "end_year": 1973,
            "organization": "Göteborgs Universitet",
            "location": {
                "name": "Göteborg",
                "latitude": 57.70887,
                "longitude": 11.97456,
                "formatted_address": "Gothenburg, Sweden"
            },
            "country_code": null
        },
        {
            "position": "ordförande",
            "start_year": 1975,
            "end_year": null,
            "organization": "Kungliga Vetenskaps- och Vitterhetssamhället i Göteborg",
            "location": {
                "name": "Göteborg",
                "latitude": 57.70887,
                "longitude": 11.97456,
                "formatted_address": "Gothenburg, Sweden"
            },
            "country_code": null
        }
    ],
    "person": {
        "first_name": "A",
        "last_name": "Dahlberg",
        "middle_name": "Torsten",
        "gender": "Male",
        "birth_date": "18-08-1906",
        "birth_place": {
            "name": "Lackalänga, Malmöhus Län",
            "latitude": 55.77353780000001,
            "longitude": 13.1130647,
            "formatted_address": "Lackalänga, 244 60 Furulund, Sweden"
        },
        "occupation": {
            "occupation": "professor",
            "occupation_english": "professor",
            "hisco_code_swedish": "13100.0",
            "hisco_description_swedish": "University and Higher Education Teacher, Subject Unknown",
            "hisco_code_english": "13100.0",
            "hisco_description_english": "University and Higher Education Teacher, Subject Unknown"
        },
        "parents": [
            {
                "first_name": "Anders",
                "last_name": "Dahlberg",
                "middle_name": null,
                "gender": "Male",
                "occupation": {
                    "occupation": "överlärare",
                    "occupation_english": null,
                    "hisco_code_swedish": "13000.0",
                    "hisco_description_swedish": "Teacher, Level and Subject Unknown"
                }
            },
            {
                "first_name": "Hilda",
                "last_name": "Johansson",
                "middle_name": null,
                "gender": "Female",
                "occupation": null
            }
        ]
    },
    "academic_positions": [
        {
            "position": "filosofie doktor",
            "position_english": "Doctor of Philosophy",
            "institution": "Lunds Universitet",
            "department": null,
            "start_year": 1934,
            "end_year": null,
            "field": null
        },
        {
            "position": "docent",
            "position_english": "docent",
            "institution": "Lunds Universitet",
            "department": null,
            "start_year": 1935,
            "end_year": 1945,
            "field": "tyska språket"
        },
        {
            "position": "professor",
            "position_english": "professor",
            "institution": "Göteborgs Universitet",
            "department": null,
            "start_year": 1951,
            "end_year": 1973,
            "field": "tyska språket"
        }
    ],
    "achievements": null,
    "awards": null,
    "board_memberships": null,
    "committee_memberships": null,
    "community_involvement": null,
    "current_location": {
        "name": "Göteborg",
        "latitude": 57.70887,
        "longitude": 11.97456,
        "formatted_address": "Gothenburg, Sweden"
    },
    "education": [
        {
            "degree": "filosofie kandidat",
            "degree_level": "Bachelor's",
            "year": "1934",
            "institution": "Lunds Universitet"
        }
    ],
    "family": {
        "spouse": {
            "first_name": "Sigrid",
            "last_name": "Floderus",
            "middle_name": null,
            "gender": "Female",
            "birth_date": null,
            "birth_place": null,
            "occupation": null,
            "parents": [
                {
                    "first_name": "Styrbjörn",
                    "last_name": "Floderus",
                    "middle_name": null,
                    "gender": "Male",
                    "occupation": {
                        "occupation": "ingenjör",
                        "occupation_english": "engineer",
                        "hisco_code_swedish": "2000.0",
                        "hisco_description_swedish": "Engineer, Specialisation Unknown",
                        "hisco_code_english": "84100.0",
                        "hisco_description_english": "Machinery Fitters and Machine Assemblers"
                    }
                },
                {
                    "first_name": "Annie",
                    "last_name": "Nyberg",
                    "middle_name": null,
                    "gender": "Female",
                    "occupation": null
                }
            ]
        },
        "marriage_year": "1940",
        "divorce_year": null,
        "children": null
    },
    "hobbies": null,
    "honorary_titles": null,
    "honors": null,
    "languages_spoken": null,
    "leadership_roles": null,
    "military_service": null,
    "political_positions": null,
    "publications": [
        {
            "title": "Die Mundart von Dorste I",
            "year": "1934",
            "type": "doktorsavhandling",
            "editions": null,
            "publisher": null,
            "reception": null,
            "signature": null,
            "volumes": null
        },
        {
            "title": "Die Mundart von Dorste II",
            "year": "1937",
            "type": "okänd",
            "editions": null,
            "publisher": null,
            "reception": null,
            "signature": null,
            "volumes": null
        },
        {
            "title": "Studien über den Wortschatz Süd-hannovers",
            "year": "1941",
            "type": "okänd",
            "editions": null,
            "publisher": null,
            "reception": null,
            "signature": null,
            "volumes": null
        },
        {
            "title": "Das moselfränkische Rosengartenfragment",
            "year": "1947",
            "type": "okänd",
            "editions": null,
            "publisher": null,
            "reception": null,
            "signature": null,
            "volumes": null
        },
        {
            "title": "Zwei unberücksichtigte mittelhochdeutsche Laurinversionen",
            "year": "1948",
            "type": "okänd",
            "editions": null,
            "publisher": null,
            "reception": null,
            "signature": null,
            "volumes": null
        },
        {
            "title": "Zum dänischen Lavrin und niederdeutschen Lorin",
            "year": "1950",
            "type": "okänd",
            "editions": null,
            "publisher": null,
            "reception": null,
            "signature": null,
            "volumes": null
        },
        {
            "title": "Mittelhochdeutsch wurpoz ’radix’, boze ’Flachsbündel’, boz ’Stoss’",
            "year": "1955",
            "type": "okänd",
            "editions": null,
            "publisher": null,
            "reception": null,
            "signature": null,
            "volumes": null
        },
        {
            "title": "Brandaniana",
            "year": "1958",
            "type": "okänd",
            "editions": null,
            "publisher": null,
            "reception": null,
            "signature": null,
            "volumes": null
        },
        {
            "title": "Mittelniéderdeutsche Suffixabstrakta",
            "year": "1962",
            "type": "okänd",
            "editions": null,
            "publisher": null,
            "reception": null,
            "signature": null,
            "volumes": null
        },
        {
            "title": "Die Dransfelder Hasenjagd vom Jahre 1660",
            "year": "1970",
            "type": "okänd",
            "editions": null,
            "publisher": null,
            "reception": null,
            "signature": null,
            "volumes": null
        },
        {
            "title": "Till Österland vill jag fara’ und das sog Ostlandlied",
            "year": "1972",
            "type": "okänd",
            "editions": null,
            "publisher": null,
            "reception": null,
            "signature": null,
            "volumes": null
        },
        {
            "title": "Flurnamen in Dorste an Harz",
            "year": "1974",
            "type": "okänd",
            "editions": null,
            "publisher": null,
            "reception": null,
            "signature": null,
            "volumes": null
        }
    ],
    "travels": null
}