{
    "career": [
        {
            "position": "exportkorrespondent",
            "start_year": 1920,
            "end_year": 1925,
            "organization": "Sandvikens jernverks aktiebolag",
            "location": null,
            "country_code": null
        },
        {
            "position": "exportkorrespondent",
            "start_year": 1925,
            "end_year": 1927,
            "organization": "Uddeholms aktiebolag",
            "location": null,
            "country_code": null
        },
        {
            "position": "exportkorrespondent",
            "start_year": 1927,
            "end_year": 1934,
            "organization": "Uddeholmstahl GmbH",
            "location": {
                "name": "Dusseldorf",
                "latitude": 51.2230411,
                "longitude": 6.7824545,
                "formatted_address": "40 Düsseldorf, Germany"
            },
            "country_code": null
        },
        {
            "position": "avdelningschef",
            "start_year": 1934,
            "end_year": 1944,
            "organization": "Uddeholms aktiebolag",
            "location": null,
            "country_code": null
        },
        {
            "position": "försäljningschef",
            "start_year": 1944,
            "end_year": 1947,
            "organization": "aktiebolag Uddeholmsagenturen",
            "location": {
                "name": "Göteborg",
                "latitude": 57.70887,
                "longitude": 11.97456,
                "formatted_address": "Gothenburg, Sweden"
            },
            "country_code": null
        },
        {
            "position": "intendent",
            "start_year": 1947,
            "end_year": 1953,
            "organization": "Uddeholms aktiebolag",
            "location": null,
            "country_code": null
        },
        {
            "position": "intendent",
            "start_year": 1953,
            "end_year": 1956,
            "organization": "Hellefors bruks aktiebolag",
            "location": null,
            "country_code": null
        },
        {
            "position": "direktör",
            "start_year": 1956,
            "end_year": 1967,
            "organization": "Uddeholms aktiebolag",
            "location": null,
            "country_code": null
        }
    ],
    "person": {
        "first_name": "G",
        "last_name": "Rosenblad",
        "middle_name": "Hjalmar",
        "gender": "Male",
        "birth_date": "25-09-1901",
        "birth_place": {
            "name": "Högbo, Gävleborgs Län",
            "latitude": 60.6628609,
            "longitude": 16.8013681,
            "formatted_address": "811 92 Högbo, Sweden"
        },
        "occupation": {
            "occupation": "direktör",
            "occupation_english": "director",
            "hisco_code_swedish": "21110.0",
            "hisco_description_swedish": "General Manager",
            "hisco_code_english": "21000.0",
            "hisco_description_english": "Manager, Specialisation Unknown"
        },
        "parents": [
            {
                "first_name": "Gustaf",
                "last_name": "Rosenblad",
                "middle_name": null,
                "gender": "Male",
                "occupation": {
                    "occupation": "fabrikör",
                    "occupation_english": "manufacturer"
                }
            },
            {
                "first_name": "Lina",
                "last_name": "Broberg",
                "middle_name": null,
                "gender": "Female",
                "occupation": null
            }
        ]
    },
    "academic_positions": null,
    "achievements": null,
    "awards": null,
    "board_memberships": [
        {
            "position": "styrelseledamot",
            "organization": "Berlingske Tidende"
        }
    ],
    "committee_memberships": null,
    "community_involvement": null,
    "current_location": {
        "name": "Köpenhamn",
        "latitude": 55.6760968,
        "longitude": 12.5683371,
        "formatted_address": "Copenhagen, Denmark"
    },
    "education": [
        {
            "degree": "Schartaus handelsinstitut",
            "degree_level": "Schooling",
            "year": "1920",
            "institution": "Schartaus handelsinstitut"
        }
    ],
    "family": {
        "spouse": {
            "first_name": "Ingeborg",
            "last_name": "Thorn",
            "middle_name": null,
            "gender": "Female",
            "birth_date": "08-01-1908",
            "birth_place": null,
            "occupation": null,
            "parents": [
                {
                    "first_name": "Waldemar",
                    "last_name": "Thorn",
                    "middle_name": null,
                    "gender": "Male",
                    "occupation": {
                        "occupation": "docent",
                        "occupation_english": "docent",
                        "hisco_code_swedish": "99999.0",
                        "hisco_description_swedish": "Unspecified worktitle or several titles",
                        "hisco_code_english": "13100.0",
                        "hisco_description_english": "University and Higher Education Teacher, Subject Unknown"
                    }
                },
                {
                    "first_name": "Hedwig",
                    "last_name": "Berling",
                    "middle_name": null,
                    "gender": "Female",
                    "occupation": null
                }
            ]
        },
        "marriage_year": "1934",
        "divorce_year": null,
        "children": null
    },
    "hobbies": null,
    "honorary_titles": null,
    "honors": null,
    "languages_spoken": null,
    "leadership_roles": null,
    "military_service": null,
    "political_positions": null,
    "publications": null,
    "travels": null
}