{
    "career": [
        {
            "position": "Byggningsinspektör",
            "start_year": 1945,
            "end_year": 1945,
            "organization": "Stockholms stads byggnadsnämnd",
            "location": {
                "name": "Stockholm",
                "latitude": 59.3327036,
                "longitude": 18.0656255,
                "formatted_address": "Stockholm, Sweden"
            },
            "country_code": null
        },
        {
            "position": "Arbetsledare",
            "start_year": 1946,
            "end_year": 1946,
            "organization": "Aktiebolag Skånska Cementgjuteriet",
            "location": null,
            "country_code": null
        },
        {
            "position": "Planerings- och offertingenjör",
            "start_year": 1947,
            "end_year": 1949,
            "organization": "Aktiebolag Atlas Diesel",
            "location": null,
            "country_code": null
        },
        {
            "position": "Försäljningsingenjör",
            "start_year": 1949,
            "end_year": 1951,
            "organization": "A Johnson & Co",
            "location": null,
            "country_code": null
        },
        {
            "position": "Direktörsassistent",
            "start_year": 1957,
            "end_year": 1960,
            "organization": "Aktiebolag Atomenergi",
            "location": null,
            "country_code": null
        },
        {
            "position": "Personalchef",
            "start_year": 1960,
            "end_year": 1961,
            "organization": "Aktiebolag Atomenergi",
            "location": null,
            "country_code": null
        },
        {
            "position": "Direktörsassistent",
            "start_year": 1961,
            "end_year": 1965,
            "organization": "Sveriges Privatanställdas Pensionskassa",
            "location": null,
            "country_code": null
        },
        {
            "position": "Biträdande Direktör",
            "start_year": 1965,
            "end_year": 1968,
            "organization": "Sveriges Privatanställdas Pensionskassa",
            "location": null,
            "country_code": null
        },
        {
            "position": "Direktör",
            "start_year": 1968,
            "end_year": 1969,
            "organization": "Sveriges Privatanställdas Pensionskassa",
            "location": null,
            "country_code": null
        },
        {
            "position": "Ekonomidirektör och chef för ekonomiavdelningen",
            "start_year": 1969,
            "end_year": 1976,
            "organization": "Sveriges Privatanställdas Pensionskassa",
            "location": null,
            "country_code": null
        },
        {
            "position": "Chef för ekonomisk utredning",
            "start_year": 1976,
            "end_year": null,
            "organization": "Sveriges Privatanställdas Pensionskassa",
            "location": null,
            "country_code": null
        }
    ],
    "person": {
        "first_name": "J",
        "last_name": "von Essen",
        "middle_name": "Christer A",
        "gender": "Male",
        "birth_date": "27-03-1921",
        "birth_place": {
            "name": "Daretorp, Skaraborgs Län",
            "latitude": 58.13925069999999,
            "longitude": 14.0201411,
            "formatted_address": "522 91 Daretorp, Sweden"
        },
        "occupation": {
            "occupation": "Direktör",
            "occupation_english": "Director",
            "hisco_code_swedish": "21110.0",
            "hisco_description_swedish": "General Manager",
            "hisco_code_english": "21000.0",
            "hisco_description_english": "Manager, Specialisation Unknown"
        },
        "parents": [
            {
                "first_name": "Allan",
                "last_name": "von Essen",
                "middle_name": null,
                "gender": "Male",
                "occupation": {
                    "occupation": "Jägmästare",
                    "occupation_english": "Forestry Officer",
                    "hisco_code_swedish": "21230.0",
                    "hisco_description_swedish": "Farm Manager",
                    "hisco_code_english": "63220.0",
                    "hisco_description_english": "Forest Supervisor"
                }
            },
            {
                "first_name": "Margit",
                "last_name": "Amundson",
                "middle_name": null,
                "gender": "Female",
                "occupation": null
            }
        ]
    },
    "academic_positions": null,
    "achievements": null,
    "awards": null,
    "board_memberships": null,
    "committee_memberships": null,
    "community_involvement": null,
    "current_location": {
        "name": "Stockholm",
        "latitude": 59.3327036,
        "longitude": 18.0656255,
        "formatted_address": "Stockholm, Sweden"
    },
    "education": [
        {
            "degree": "KTH",
            "degree_level": "Master's",
            "year": "1945",
            "institution": "Kungliga Tekniska Högskolan"
        },
        {
            "degree": "DHS",
            "degree_level": "Bachelor's",
            "year": "1957",
            "institution": "DjHögskolan"
        }
    ],
    "family": {
        "spouse": {
            "first_name": "Gunnel",
            "last_name": "Wahren",
            "middle_name": null,
            "gender": "Female",
            "birth_date": "1922",
            "birth_place": null,
            "occupation": {
                "occupation": "Fotograf",
                "occupation_english": "Photographer",
                "hisco_code_swedish": "16310.0",
                "hisco_description_swedish": "Photographer, General",
                "hisco_code_english": "16310.0",
                "hisco_description_english": "Photographer, General"
            },
            "parents": [
                {
                    "first_name": "Ernst",
                    "last_name": "Wahren",
                    "middle_name": null,
                    "gender": "Male",
                    "occupation": {
                        "occupation": "Disponent",
                        "occupation_english": "Manager",
                        "hisco_code_swedish": "21110.0",
                        "hisco_description_swedish": "General Manager",
                        "hisco_code_english": "21000.0",
                        "hisco_description_english": "Manager, Specialisation Unknown"
                    }
                },
                {
                    "first_name": "Margareta",
                    "last_name": "Ljungholm",
                    "middle_name": null,
                    "gender": "Female",
                    "occupation": null
                }
            ]
        },
        "marriage_year": "1952",
        "divorce_year": null,
        "children": null
    },
    "hobbies": null,
    "honorary_titles": null,
    "honors": null,
    "languages_spoken": null,
    "leadership_roles": null,
    "military_service": "Fänrik A 1 reserv 1942, löjtnant 1945, kapten VVK sedan 1952",
    "political_positions": null,
    "publications": null,
    "travels": null
}