{
    "career": [
        {
            "position": "Anställd",
            "start_year": 1944,
            "end_year": null,
            "organization": "Länsstyrelsen Stockholms Län",
            "location": {
                "name": "Stockholms Län",
                "latitude": 59.4069048,
                "longitude": 18.8230665,
                "formatted_address": "Stockholm County, Sweden"
            },
            "country_code": "SWE"
        },
        {
            "position": "Extra ordinarie taxeringsinspektör",
            "start_year": 1948,
            "end_year": null,
            "organization": "Västernorrlands Län",
            "location": {
                "name": "Västernorrlands Län",
                "latitude": 62.98552900000001,
                "longitude": 18.1258604,
                "formatted_address": "Västernorrland County, Sweden"
            },
            "country_code": "SWE"
        },
        {
            "position": "Förste taxeringsinspektör",
            "start_year": 1952,
            "end_year": null,
            "organization": null,
            "location": null,
            "country_code": null
        },
        {
            "position": "Biträdande taxeringsintendent",
            "start_year": 1952,
            "end_year": null,
            "organization": "Västernorrlands Län",
            "location": {
                "name": "Västernorrlands Län",
                "latitude": 62.98552900000001,
                "longitude": 18.1258604,
                "formatted_address": "Västernorrland County, Sweden"
            },
            "country_code": "SWE"
        },
        {
            "position": "Tillförordnad taxeringsintendent",
            "start_year": 1958,
            "end_year": null,
            "organization": "Kopparbergs Län",
            "location": {
                "name": "Kopparbergs Län",
                "latitude": 61.0917012,
                "longitude": 14.6663653,
                "formatted_address": "Dalarna County, Sweden"
            },
            "country_code": "SWE"
        },
        {
            "position": "Byråchef",
            "start_year": 1959,
            "end_year": null,
            "organization": "Riksskattenämnden",
            "location": null,
            "country_code": null
        },
        {
            "position": "Landskamrerare",
            "start_year": 1964,
            "end_year": null,
            "organization": "Jämtlands Län",
            "location": {
                "name": "Östersund",
                "latitude": 63.1766832,
                "longitude": 14.6360681,
                "formatted_address": "Östersund, Sweden"
            },
            "country_code": "SWE"
        }
    ],
    "person": {
        "first_name": "Bengt",
        "last_name": "Bohman",
        "middle_name": "A H",
        "gender": "Male",
        "birth_date": "20-04-1915",
        "birth_place": {
            "name": "Stockholm",
            "latitude": 59.3327036,
            "longitude": 18.0656255,
            "formatted_address": "Stockholm, Sweden"
        },
        "occupation": {
            "occupation": "Landskamrerare",
            "occupation_english": "Chief Accountant of the County",
            "hisco_code_swedish": "11010.0",
            "hisco_description_swedish": "Accountant, General",
            "hisco_code_english": "11010.0",
            "hisco_description_english": "Accountant, General"
        },
        "parents": [
            {
                "first_name": "Hans",
                "last_name": "Bohman",
                "middle_name": null,
                "gender": "Male",
                "occupation": {
                    "occupation": "förste assess",
                    "occupation_english": "Senior Assessor",
                    "hisco_code_swedish": "12210.0",
                    "hisco_description_swedish": "Judge",
                    "hisco_code_english": "31030.0",
                    "hisco_description_english": "Tax Assessor"
                }
            },
            {
                "first_name": "Dolly",
                "last_name": "Lindström",
                "middle_name": null,
                "gender": "Female",
                "occupation": null
            }
        ]
    },
    "academic_positions": null,
    "achievements": null,
    "awards": [
        "Riddare av Nordstjärneorden (RNO)"
    ],
    "board_memberships": [
        {
            "position": "Styrelseledamot",
            "organization": "Sveriges Yngre Juristers Förening (SYJF)"
        },
        {
            "position": "Styrelseledamot",
            "organization": "Sveriges Juristförbund"
        }
    ],
    "committee_memberships": null,
    "community_involvement": null,
    "current_location": {
        "name": "Östersund",
        "latitude": 63.1766832,
        "longitude": 14.6360681,
        "formatted_address": "Östersund, Sweden"
    },
    "education": [
        {
            "degree": "Studentexamen",
            "degree_level": "Schooling",
            "year": "1933",
            "institution": "Djursholm"
        },
        {
            "degree": "Juristkandidatexamen",
            "degree_level": "Master's",
            "year": "1940",
            "institution": "Stockholm"
        }
    ],
    "family": {
        "spouse": {
            "first_name": "Britt-Marie",
            "last_name": "Månsson",
            "middle_name": null,
            "gender": "Female",
            "birth_date": null,
            "birth_place": null,
            "occupation": null,
            "parents": [
                {
                    "first_name": "Birger",
                    "last_name": "Månsson",
                    "middle_name": null,
                    "gender": "Male",
                    "occupation": {
                        "occupation": "Konsul",
                        "occupation_english": "Consul",
                        "hisco_code_swedish": "20210.0",
                        "hisco_description_swedish": "Government Administrator",
                        "hisco_code_english": "20210.0",
                        "hisco_description_english": "Government Administrator"
                    }
                },
                {
                    "first_name": "Gurli",
                    "last_name": "Janzon",
                    "middle_name": null,
                    "gender": "Female",
                    "occupation": null
                }
            ]
        },
        "marriage_year": "1942",
        "divorce_year": null,
        "children": [
            {
                "first_name": "Inger",
                "last_name": "Bohman",
                "middle_name": null,
                "gender": "Female",
                "birth_year": "1949"
            },
            {
                "first_name": "Agneta",
                "last_name": "Bohman",
                "middle_name": null,
                "gender": "Female",
                "birth_year": "1952"
            }
        ]
    },
    "hobbies": null,
    "honorary_titles": null,
    "honors": null,
    "languages_spoken": null,
    "leadership_roles": null,
    "military_service": null,
    "political_positions": null,
    "publications": null,
    "travels": null
}