{
    "career": [
        {
            "position": "Extra ordinarie och ordinarie amanuens i histologi",
            "start_year": 1920,
            "end_year": 1922,
            "organization": "Lund",
            "location": {
                "name": "Lund",
                "latitude": 55.7046601,
                "longitude": 13.1910073,
                "formatted_address": "Lund, Sweden"
            },
            "country_code": null
        },
        {
            "position": "Assistentläkare och tillförordnad underläkare",
            "start_year": 1924,
            "end_year": 1925,
            "organization": "Lasarett i Lidköping",
            "location": {
                "name": "Lidköping",
                "latitude": 58.5035047,
                "longitude": 13.1570768,
                "formatted_address": "Lidköping, Sweden"
            },
            "country_code": null
        },
        {
            "position": "Assistentläkare",
            "start_year": 1927,
            "end_year": null,
            "organization": "Avdelning för medicinsk tuberkulos å S:t Görans sjukhus",
            "location": {
                "name": "Stockholm",
                "latitude": 59.3327036,
                "longitude": 18.0656255,
                "formatted_address": "Stockholm, Sweden"
            },
            "country_code": null
        },
        {
            "position": "Tillförordnad underläkare",
            "start_year": 1927,
            "end_year": null,
            "organization": "Lots sanatorium",
            "location": null,
            "country_code": null
        },
        {
            "position": "Tillförordnad och ordinarie amanuens",
            "start_year": 1927,
            "end_year": 1928,
            "organization": "Dermato-syfilidologiska klinik å Karolinska institutet",
            "location": null,
            "country_code": null
        },
        {
            "position": "Tillförordnad underläkare",
            "start_year": 1928,
            "end_year": null,
            "organization": "Avdelning för hud- och könssjukdomar å S:t Görans sjukhus",
            "location": {
                "name": "Stockholm",
                "latitude": 59.3327036,
                "longitude": 18.0656255,
                "formatted_address": "Stockholm, Sweden"
            },
            "country_code": null
        },
        {
            "position": "Tillförordnad underläkare",
            "start_year": 1928,
            "end_year": null,
            "organization": "Avdelning för medicinsk tuberkulos å S:t Görans sjukhus",
            "location": {
                "name": "Stockholm",
                "latitude": 59.3327036,
                "longitude": 18.0656255,
                "formatted_address": "Stockholm, Sweden"
            },
            "country_code": null
        },
        {
            "position": "Underläkare",
            "start_year": 1928,
            "end_year": null,
            "organization": "Lasarett i Örnsköldsvik",
            "location": {
                "name": "Örnsköldsvik",
                "latitude": 63.29004740000001,
                "longitude": 18.7166166,
                "formatted_address": "Örnsköldsvik, Sweden"
            },
            "country_code": null
        },
        {
            "position": "Tillförordnad underläkare",
            "start_year": 1928,
            "end_year": null,
            "organization": "Medicinska avdelningen i Örnsköldsvik",
            "location": {
                "name": "Örnsköldsvik",
                "latitude": 63.29004740000001,
                "longitude": 18.7166166,
                "formatted_address": "Örnsköldsvik, Sweden"
            },
            "country_code": null
        },
        {
            "position": "Underläkare",
            "start_year": 1928,
            "end_year": 1929,
            "organization": null,
            "location": null,
            "country_code": null
        },
        {
            "position": "Tillförordnad lasarettsläkare",
            "start_year": 1928,
            "end_year": 1929,
            "organization": null,
            "location": null,
            "country_code": null
        },
        {
            "position": "Underläkare",
            "start_year": 1930,
            "end_year": 1931,
            "organization": "Avdelning för hud- och könssjukdomar vid S:t Görans sjukhus",
            "location": {
                "name": "Stockholm",
                "latitude": 59.3327036,
                "longitude": 18.0656255,
                "formatted_address": "Stockholm, Sweden"
            },
            "country_code": null
        },
        {
            "position": "Tillförordnad underläkare",
            "start_year": 1930,
            "end_year": null,
            "organization": "Ekmanska sjukhuset i Göteborg",
            "location": {
                "name": "Göteborg",
                "latitude": 57.70887,
                "longitude": 11.97456,
                "formatted_address": "Gothenburg, Sweden"
            },
            "country_code": null
        },
        {
            "position": "Underläkare",
            "start_year": 1931,
            "end_year": 1934,
            "organization": "Medicinska avdelningen å S:t Eriks sjukhus",
            "location": {
                "name": "Stockholm",
                "latitude": 59.3327036,
                "longitude": 18.0656255,
                "formatted_address": "Stockholm, Sweden"
            },
            "country_code": null
        },
        {
            "position": "Extra stadsdistriktsläkare",
            "start_year": 1934,
            "end_year": null,
            "organization": "Stockholm",
            "location": {
                "name": "Stockholm",
                "latitude": 59.3327036,
                "longitude": 18.0656255,
                "formatted_address": "Stockholm, Sweden"
            },
            "country_code": null
        },
        {
            "position": "Ordinarie distriktsläkare",
            "start_year": 1939,
            "end_year": null,
            "organization": "Stockholm",
            "location": {
                "name": "Stockholm",
                "latitude": 59.3327036,
                "longitude": 18.0656255,
                "formatted_address": "Stockholm, Sweden"
            },
            "country_code": null
        }
    ],
    "person": {
        "first_name": "Birger",
        "last_name": "Magnusson",
        "middle_name": null,
        "gender": "Male",
        "birth_date": "06-03-1897",
        "birth_place": {
            "name": "Jönköping",
            "latitude": 57.78261370000001,
            "longitude": 14.1617876,
            "formatted_address": "Jönköping, Sweden"
        },
        "occupation": {
            "occupation": "Legitimerad läkare, medicine licentiat",
            "occupation_english": "Licensed physician, Doctor of Medicine",
            "hisco_code_swedish": "6100.0",
            "hisco_description_swedish": "Medical Doctor, Specialisation Unknown",
            "hisco_code_english": "6100.0",
            "hisco_description_english": "Medical Doctor, Specialisation Unknown"
        },
        "parents": [
            {
                "first_name": "Anders",
                "last_name": "Magnusson",
                "middle_name": "Gustav",
                "gender": "Male",
                "occupation": {
                    "occupation": "Verkställande resehandlare",
                    "occupation_english": "Managing traveling merchant"
                }
            },
            {
                "first_name": "Hulda",
                "last_name": "Westberg",
                "middle_name": "Maria",
                "gender": "Female",
                "occupation": null
            }
        ]
    },
    "academic_positions": null,
    "achievements": null,
    "awards": null,
    "board_memberships": null,
    "committee_memberships": null,
    "community_involvement": null,
    "current_location": {
        "name": "Stockholm",
        "latitude": 59.3327036,
        "longitude": 18.0656255,
        "formatted_address": "Stockholm, Sweden"
    },
    "education": [
        {
            "degree": "Studentexamen",
            "degree_level": "Schooling",
            "year": "1917",
            "institution": "Jönköping"
        },
        {
            "degree": "Medicine kandidat",
            "degree_level": "Bachelor's",
            "year": "1922",
            "institution": "Lund"
        },
        {
            "degree": "Medicine licentiat",
            "degree_level": "Master's",
            "year": "1927",
            "institution": "Stockholm"
        }
    ],
    "family": {
        "spouse": {
            "first_name": "Säga",
            "last_name": "Tenlén",
            "middle_name": null,
            "gender": "Female",
            "birth_date": null,
            "birth_place": null,
            "occupation": {
                "occupation": "Medicine licentiat",
                "occupation_english": "Doctor of Medicine",
                "hisco_code_swedish": "6100.0",
                "hisco_description_swedish": "Medical Doctor, Specialisation Unknown",
                "hisco_code_english": "6100.0",
                "hisco_description_english": "Medical Doctor, Specialisation Unknown"
            },
            "parents": null
        },
        "marriage_year": "1936",
        "divorce_year": null,
        "children": [
            {
                "first_name": "Anders",
                "last_name": "Magnusson",
                "middle_name": "Oskar",
                "gender": "Male",
                "birth_year": "1939"
            },
            {
                "first_name": "Torsten",
                "last_name": "Magnusson",
                "middle_name": "Birger",
                "gender": "Male",
                "birth_year": "1940"
            }
        ]
    },
    "hobbies": null,
    "honorary_titles": null,
    "honors": null,
    "languages_spoken": null,
    "leadership_roles": null,
    "military_service": null,
    "political_positions": null,
    "publications": null,
    "travels": null
}