{
    "career": [
        {
            "position": "anställd",
            "start_year": 1925,
            "end_year": null,
            "organization": "Aktiebolaget Vattenbyggnadsbyrån",
            "location": "Stockholm",
            "country_code": null
        }
    ],
    "person": {
        "first_name": "Olof",
        "last_name": "Ljung",
        "middle_name": "Egil",
        "gender": "Male",
        "birth_date": "14-02-1900",
        "birth_place": "Sollefteå",
        "occupation": {
            "occupation": "civilingenjör",
            "occupation_english": null,
            "hisco_code_swedish": "2210.0",
            "hisco_description_swedish": "Civil Engineer, General"
        },
        "parents": [
            {
                "first_name": "Per",
                "last_name": "Ljung",
                "middle_name": "Emil",
                "gender": "Male",
                "occupation": {
                    "occupation": "stat:inspektör",
                    "occupation_english": null
                }
            },
            {
                "first_name": "Ellen",
                "last_name": "Östman",
                "middle_name": null,
                "gender": "Female",
                "occupation": null
            }
        ]
    },
    "academic_positions": null,
    "achievements": null,
    "awards": null,
    "board_memberships": [
        {
            "position": "Styrelseledamot",
            "organization": "Aktiebolaget Vattenbyggnadsbyrån"
        }
    ],
    "committee_memberships": null,
    "community_involvement": null,
    "current_location": "Stockholm",
    "education": [
        {
            "degree": "studentexamen",
            "degree_level": "Schooling",
            "year": "1919",
            "institution": "Uddevalla"
        },
        {
            "degree": "filosofie kandidat",
            "degree_level": "Bachelor's",
            "year": "1923",
            "institution": "KTH"
        }
    ],
    "family": {
        "spouse": {
            "first_name": "Betty",
            "last_name": "Abrahamsen",
            "middle_name": null,
            "gender": "Female",
            "birth_date": null,
            "birth_place": null,
            "occupation": null,
            "parents": [
                {
                    "first_name": "John",
                    "last_name": "Abrahamsen",
                    "middle_name": "L.",
                    "gender": "Male",
                    "occupation": {
                        "occupation": "sjökaptens",
                        "occupation_english": null,
                        "hisco_code_swedish": "4217.0",
                        "hisco_description_swedish": "Ship's Master (Sea or Inland Waterways)"
                    }
                },
                {
                    "first_name": "Mimmi",
                    "last_name": "Carlsson",
                    "middle_name": null,
                    "gender": "Female",
                    "occupation": null
                }
            ]
        },
        "marriage_year": "1927",
        "divorce_year": null,
        "children": null
    },
    "hobbies": null,
    "honorary_titles": null,
    "honors": null,
    "languages_spoken": null,
    "leadership_roles": null,
    "military_service": null,
    "political_positions": null,
    "publications": null,
    "travels": [
        {
            "country": "Finland",
            "country_code": "FIN",
            "year": null
        },
        {
            "country": "Ryssland",
            "country_code": "RUS",
            "year": null
        },
        {
            "country": "Lettland",
            "country_code": "LVA",
            "year": null
        },
        {
            "country": "Polen",
            "country_code": "POL",
            "year": null
        },
        {
            "country": "Rumänien",
            "country_code": "ROU",
            "year": null
        },
        {
            "country": "Malackahalvön",
            "country_code": "MYS",
            "year": null
        },
        {
            "country": "Siam",
            "country_code": "THA",
            "year": null
        },
        {
            "country": "Venezuela",
            "country_code": "VEN",
            "year": null
        }
    ]
}