{
    "career": [
        {
            "position": "Amanuens",
            "start_year": 1907,
            "end_year": null,
            "organization": "Jordbruksdepartementet",
            "location": null,
            "country_code": null
        },
        {
            "position": "Kanslisekreterare",
            "start_year": 1913,
            "end_year": null,
            "organization": "Jordbruksdepartementet",
            "location": null,
            "country_code": null
        },
        {
            "position": "Förste Kanslisekreterare",
            "start_year": 1917,
            "end_year": 1945,
            "organization": "Jordbruksdepartementet",
            "location": null,
            "country_code": null
        },
        {
            "position": "Kansliråd",
            "start_year": 1936,
            "end_year": null,
            "organization": "Kunglig Majestäts kansli",
            "location": null,
            "country_code": null
        }
    ],
    "person": {
        "first_name": "Curt",
        "last_name": "Rohtlieb",
        "middle_name": "V",
        "gender": "Male",
        "birth_date": "03-09-1880",
        "birth_place": "Stockholm",
        "occupation": {
            "occupation": "Kansliråd",
            "occupation_english": null,
            "hisco_code_swedish": "20210.0",
            "hisco_description_swedish": "Government Administrator"
        },
        "parents": [
            {
                "first_name": "Herm",
                "last_name": "R",
                "middle_name": null,
                "gender": "Male",
                "occupation": {
                    "occupation": "Revisionssekreterare",
                    "occupation_english": null,
                    "hisco_code_swedish": "30000.0",
                    "hisco_description_swedish": "Clerical or Related Worker, Specialisation Unknown"
                }
            },
            {
                "first_name": "Maria",
                "last_name": "von Willebrand",
                "middle_name": null,
                "gender": "Female",
                "occupation": null
            }
        ]
    },
    "academic_positions": null,
    "achievements": null,
    "awards": null,
    "board_memberships": null,
    "committee_memberships": null,
    "community_involvement": null,
    "current_location": "Djursholm",
    "education": [
        {
            "degree": "Juridik Utr Kandidat",
            "degree_level": "Master's",
            "year": "1904",
            "institution": "Uppsala"
        },
        {
            "degree": "Juridik Doktor",
            "degree_level": "Doctorate",
            "year": "1921",
            "institution": "Lund"
        }
    ],
    "family": {
        "spouse": {
            "first_name": "Malin",
            "last_name": "Hjärne",
            "middle_name": null,
            "gender": "Female",
            "birth_date": null,
            "birth_place": null,
            "occupation": null,
            "parents": [
                {
                    "first_name": "Urban",
                    "last_name": "Hjärne",
                    "middle_name": null,
                    "gender": "Male",
                    "occupation": {
                        "occupation": "Skogsförvaltare",
                        "occupation_english": null,
                        "hisco_code_swedish": "21230.0",
                        "hisco_description_swedish": "Farm Manager"
                    }
                },
                {
                    "first_name": "Amalia",
                    "last_name": "Nordlander",
                    "middle_name": null,
                    "gender": "Female",
                    "occupation": null
                }
            ]
        },
        "marriage_year": "1924",
        "divorce_year": null,
        "children": null
    },
    "hobbies": null,
    "honorary_titles": null,
    "honors": null,
    "languages_spoken": null,
    "leadership_roles": null,
    "military_service": null,
    "political_positions": null,
    "publications": [
        {
            "title": "Skrifter i nationalekonomi, agrarpolitik och historia",
            "year": "None",
            "type": "None",
            "editions": null,
            "publisher": null,
            "reception": null,
            "signature": null,
            "volumes": null
        }
    ],
    "travels": null
}