{
    "career": [
        {
            "position": "Adjunkt",
            "start_year": 1954,
            "organization": "Järnåkraskolan",
            "location": "None",
            "country_code": null
        }
    ],
    "person": {
        "first_name": "Gun",
        "last_name": "Bengtsson",
        "middle_name": "K M",
        "gender": "Female",
        "birth_date": "10-12-1929",
        "birth_place": "Linneryd, Kronobergs Län",
        "occupation": {
            "occupation": "Adjunkt",
            "occupation_english": "Lecturer",
            "hisco_code_swedish": "13030.0",
            "hisco_description_swedish": "Teacher, Level and Subject Unknown, Not Primary Education",
            "hisco_code_english": "13100.0",
            "hisco_description_english": "University and Higher Education Teacher, Subject Unknown"
        }
    },
    "academic_positions": null,
    "achievements": [
        {
            "title": "Översättare",
            "field": "Litteratur och dramatik",
            "year": "från 1955",
            "significance": "Översättningar tillsammans med Nils A Bengtsson av skönlitteratur och dramatik från tyska, engelska, franska, danska och norska.",
            "recognized_by": null
        },
        {
            "title": "Recensent",
            "field": "Journalistik",
            "year": "från 1958",
            "significance": "Recensent för Sydsvenska Dagbladet",
            "recognized_by": "Sydsvenska Dagbladet"
        }
    ],
    "awards": null,
    "board_memberships": null,
    "committee_memberships": null,
    "community_involvement": null,
    "current_location": "Torna Hällestad",
    "education": [
        {
            "degree": "Filosofie Magister",
            "degree_level": "Master's",
            "year": "1954",
            "institution": "Lunds Universitet"
        }
    ],
    "family": {
        "spouse": {
            "first_name": "Nils",
            "last_name": "Bengtsson",
            "middle_name": "A",
            "gender": "Male",
            "birth_date": null,
            "birth_place": null,
            "occupation": null,
            "parents": null
        },
        "marriage_year": "1954",
        "divorce_year": "1974",
        "children": null
    },
    "hobbies": null,
    "honorary_titles": null,
    "honors": null,
    "languages_spoken": null,
    "leadership_roles": null,
    "military_service": null,
    "political_positions": null,
    "publications": null,
    "travels": null
}