{
    "career": [
        {
            "position": "UDtjg",
            "start_year": 1964,
            "organization": "Paris",
            "location": "Paris",
            "country_code": "FRA"
        },
        {
            "position": "UDtjg",
            "start_year": 1964,
            "organization": "Djakarta",
            "location": "Djakarta",
            "country_code": "IDN"
        },
        {
            "position": "UDtjg",
            "start_year": 1964,
            "organization": "Stockholm",
            "location": "Stockholm",
            "country_code": "SWE"
        },
        {
            "position": "UDtjg",
            "start_year": 1964,
            "organization": "Alger",
            "location": "Alger",
            "country_code": "DZA"
        },
        {
            "position": "UDtjg",
            "start_year": 1964,
            "organization": "Rom",
            "location": "Rom",
            "country_code": "ITA"
        },
        {
            "position": "ambassadråd",
            "start_year": 1980,
            "organization": "Rom",
            "location": "Rom",
            "country_code": "ITA"
        },
        {
            "position": "ambassadråd",
            "start_year": 1981,
            "end_year": 1985,
            "organization": "Genève",
            "location": "Genève",
            "country_code": "CHE"
        },
        {
            "position": "sändebud",
            "start_year": 1985,
            "end_year": 1988,
            "organization": "Teheran",
            "location": "Teheran",
            "country_code": "IRN"
        },
        {
            "position": "departementsråd",
            "start_year": 1988,
            "end_year": 1991,
            "organization": "Utrikesdepartementet",
            "location": "Stockholm",
            "country_code": "SWE"
        },
        {
            "position": "sändebud",
            "start_year": 1992,
            "organization": "Mexico",
            "location": "Mexico",
            "country_code": "MEX"
        }
    ],
    "person": {
        "first_name": "Bo",
        "last_name": "Henrikson",
        "middle_name": "T",
        "gender": "Male",
        "birth_date": "26-11-1940",
        "birth_place": "Göteborg",
        "occupation": {
            "occupation": "departementsråd",
            "occupation_english": "Councilor"
        },
        "parents": [
            {
                "first_name": "Torsten",
                "last_name": "Henrikson",
                "gender": "Male",
                "occupation": {
                    "occupation": "kommunalråd",
                    "occupation_english": "Municipal Commissioner",
                    "hisco_code_swedish": "20110.0",
                    "hisco_description_swedish": "Legislative Official",
                    "hisco_code_english": "31090.0",
                    "hisco_description_english": "Government Executive Officials Not Elsewhere Classified"
                }
            },
            {
                "first_name": "Ester",
                "last_name": "Johansson",
                "gender": "Female",
                "occupation": null
            }
        ]
    },
    "academic_positions": null,
    "achievements": null,
    "awards": null,
    "board_memberships": null,
    "committee_memberships": null,
    "community_involvement": null,
    "current_location": "Stockholm",
    "education": [
        {
            "degree": "filosofie kandidat",
            "degree_level": "Bachelor's",
            "year": "1964",
            "institution": "Göteborgs Universitet"
        },
        {
            "degree": "politices magister",
            "degree_level": "Master's",
            "year": "1964",
            "institution": "Göteborgs Universitet"
        }
    ],
    "family": {
        "spouse": {
            "first_name": "Margareta",
            "last_name": "Collert",
            "gender": "Female",
            "birth_date": null,
            "birth_place": null,
            "occupation": null,
            "parents": [
                {
                    "first_name": "Fritz",
                    "last_name": "Collert",
                    "gender": "Male",
                    "occupation": {
                        "occupation": "försäkringsdirektör",
                        "occupation_english": "Insurance Director",
                        "hisco_code_swedish": "21110.0",
                        "hisco_description_swedish": "General Manager"
                    }
                },
                {
                    "first_name": "Karin",
                    "last_name": "Brattström",
                    "gender": "Female",
                    "occupation": null
                }
            ]
        },
        "marriage_year": "1967",
        "divorce_year": null,
        "children": null
    },
    "hobbies": null,
    "honorary_titles": null,
    "honors": null,
    "languages_spoken": null,
    "leadership_roles": null,
    "military_service": null,
    "political_positions": null,
    "publications": null,
    "travels": null
}