{
    "career": [],
    "person": {
        "first_name": "Axel",
        "last_name": "Holmberg",
        "middle_name": "Olof",
        "gender": "Male",
        "birth_date": "20-10-1893",
        "birth_place": "Stockholm",
        "occupation": null
    },
    "academic_positions": [
        {
            "position": "docent",
            "position_english": "Docent",
            "institution": "Lunds universitet",
            "department": "litteraturhistoria med poetik",
            "start_year": 1922,
            "end_year": null,
            "field": null
        },
        {
            "position": "professor",
            "position_english": "Professor",
            "institution": "Lunds universitet",
            "department": "litteraturhistoria med poetik",
            "start_year": 1937,
            "end_year": null,
            "field": null
        }
    ],
    "achievements": null,
    "awards": null,
    "board_memberships": null,
    "committee_memberships": null,
    "community_involvement": null,
    "current_location": "Lund",
    "education": [
        {
            "degree": "filosofie kandidat",
            "degree_level": "Bachelor's",
            "year": "1914",
            "institution": "Lund"
        },
        {
            "degree": "filosofie licentiat",
            "degree_level": "Master's",
            "year": "1920",
            "institution": "Lund"
        },
        {
            "degree": "filosofie doktor",
            "degree_level": "Doctorate",
            "year": "1922",
            "institution": "Lund"
        }
    ],
    "family": {
        "spouse": {
            "first_name": "Hilda",
            "last_name": "Nelander",
            "middle_name": null,
            "gender": "Female",
            "birth_date": null,
            "birth_place": null,
            "occupation": null,
            "parents": [
                {
                    "first_name": "Fr.",
                    "last_name": "Nelander",
                    "middle_name": "W.",
                    "gender": "Male",
                    "occupation": {
                        "occupation": "rådman",
                        "occupation_english": null
                    }
                },
                {
                    "first_name": "Hilda",
                    "last_name": "Dahl",
                    "middle_name": null,
                    "gender": "Female",
                    "occupation": null
                }
            ]
        },
        "marriage_year": "1916",
        "divorce_year": null,
        "children": null
    },
    "hobbies": null,
    "honorary_titles": null,
    "honors": null,
    "languages_spoken": null,
    "leadership_roles": null,
    "military_service": null,
    "political_positions": null,
    "publications": [
        {
            "title": "Frödings mystik",
            "year": "1921",
            "type": "book",
            "editions": null,
            "publisher": null,
            "reception": null,
            "signature": null,
            "volumes": null
        },
        {
            "title": "C. J. L. Almqvist",
            "year": "1922",
            "type": "book",
            "editions": null,
            "publisher": null,
            "reception": null,
            "signature": null,
            "volumes": null
        },
        {
            "title": "Litterärt",
            "year": "1924",
            "type": "book",
            "editions": null,
            "publisher": null,
            "reception": null,
            "signature": null,
            "volumes": null
        },
        {
            "title": "Madonnan o. järnjungfrun",
            "year": "1927",
            "type": "book",
            "editions": null,
            "publisher": null,
            "reception": null,
            "signature": null,
            "volumes": null
        },
        {
            "title": "På väktargången",
            "year": "1928",
            "type": "book",
            "editions": null,
            "publisher": null,
            "reception": null,
            "signature": null,
            "volumes": null
        },
        {
            "title": "Inbillningens värld",
            "year": "1927",
            "type": "book",
            "editions": null,
            "publisher": null,
            "reception": null,
            "signature": null,
            "volumes": "I-II: 1, 2"
        },
        {
            "title": "På jakt efter en världsåskådning",
            "year": "1932",
            "type": "book",
            "editions": null,
            "publisher": null,
            "reception": null,
            "signature": null,
            "volumes": null
        },
        {
            "title": "Sverige-modell 1933",
            "year": "1933",
            "type": "book",
            "editions": null,
            "publisher": null,
            "reception": null,
            "signature": null,
            "volumes": null
        },
        {
            "title": "Viktor Rydbergs lyrik",
            "year": "1935",
            "type": "book",
            "editions": null,
            "publisher": null,
            "reception": null,
            "signature": null,
            "volumes": null
        },
        {
            "title": "Den främmande passageraren",
            "year": "1937",
            "type": "book",
            "editions": null,
            "publisher": null,
            "reception": null,
            "signature": null,
            "volumes": null
        },
        {
            "title": "Roger Martin du Gard",
            "year": "1937",
            "type": "book",
            "editions": null,
            "publisher": null,
            "reception": null,
            "signature": null,
            "volumes": null
        },
        {
            "title": "Gud som haver",
            "year": "1939",
            "type": "book",
            "editions": null,
            "publisher": null,
            "reception": null,
            "signature": null,
            "volumes": null
        },
        {
            "title": "Sex kapitel om Stagnelius",
            "year": "1941",
            "type": "book",
            "editions": null,
            "publisher": null,
            "reception": null,
            "signature": null,
            "volumes": null
        },
        {
            "title": "Thomas Mann och det tredje riket",
            "year": "1942",
            "type": "book",
            "editions": null,
            "publisher": null,
            "reception": null,
            "signature": null,
            "volumes": null
        },
        {
            "title": "Tankar om rådjursstek o. annat",
            "year": "1943",
            "type": "book",
            "editions": null,
            "publisher": null,
            "reception": null,
            "signature": null,
            "volumes": null
        }
    ],
    "travels": null
}