{
    "career": [
        {
            "position": "Fänrik",
            "start_year": 1938,
            "end_year": null,
            "organization": "I 3",
            "location": null,
            "country_code": null
        },
        {
            "position": "Kapten",
            "start_year": 1946,
            "end_year": null,
            "organization": null,
            "location": null,
            "country_code": null
        },
        {
            "position": "Major",
            "start_year": 1957,
            "end_year": null,
            "organization": "I 2",
            "location": null,
            "country_code": null
        },
        {
            "position": "Överstelöjtnant",
            "start_year": 1966,
            "end_year": null,
            "organization": "I 21",
            "location": null,
            "country_code": null
        },
        {
            "position": "Överste",
            "start_year": 1972,
            "end_year": null,
            "organization": "Armén",
            "location": null,
            "country_code": null
        },
        {
            "position": "Chef",
            "start_year": 1957,
            "end_year": 1958,
            "organization": "Svenska FN-bataljonen",
            "location": "Gaza",
            "country_code": null
        },
        {
            "position": "Generalsekreterare",
            "start_year": 1974,
            "end_year": null,
            "organization": "SkidVM",
            "location": null,
            "country_code": null
        }
    ],
    "person": {
        "first_name": "Claes",
        "last_name": "Egneii",
        "middle_name": "R H V:son",
        "gender": "Male",
        "birth_date": "29-01-1916",
        "birth_place": "Lännäs, Örebro Län",
        "occupation": {
            "occupation": "Överste",
            "occupation_english": "Colonel"
        },
        "parents": [
            {
                "first_name": "Vidar",
                "last_name": "Egneii",
                "middle_name": null,
                "gender": "Male",
                "occupation": {
                    "occupation": "Överstelöjtnant",
                    "occupation_english": "Lieutenant Colonel"
                }
            },
            {
                "first_name": "Maud",
                "last_name": "Montgomery",
                "middle_name": null,
                "gender": "Female",
                "occupation": null
            }
        ]
    },
    "academic_positions": null,
    "achievements": [
        {
            "title": "SM i modern femkamp",
            "field": "Sport",
            "year": "1941",
            "significance": null,
            "recognized_by": null
        },
        {
            "title": "SM i modern femkamp",
            "field": "Sport",
            "year": "1942",
            "significance": null,
            "recognized_by": null
        },
        {
            "title": "SM i modern femkamp",
            "field": "Sport",
            "year": "1943",
            "significance": null,
            "recognized_by": null
        },
        {
            "title": "SM i modern femkamp",
            "field": "Sport",
            "year": "1945",
            "significance": null,
            "recognized_by": null
        },
        {
            "title": "SM i modern femkamp",
            "field": "Sport",
            "year": "1947",
            "significance": null,
            "recognized_by": null
        },
        {
            "title": "SM i modern femkamp",
            "field": "Sport",
            "year": "1952",
            "significance": null,
            "recognized_by": null
        },
        {
            "title": "SM i vinterfemkamp",
            "field": "Sport",
            "year": "1945",
            "significance": null,
            "recognized_by": null
        },
        {
            "title": "SM i vinterfemkamp",
            "field": "Sport",
            "year": "1948",
            "significance": null,
            "recognized_by": null
        },
        {
            "title": "Svenska Dagbladets guldmedalj",
            "field": "Sport",
            "year": "1945",
            "significance": null,
            "recognized_by": "Svenska Dagbladet"
        },
        {
            "title": "SM i lag i modern femkamp",
            "field": "Sport",
            "year": "1952",
            "significance": "OS",
            "recognized_by": null
        }
    ],
    "awards": null,
    "board_memberships": null,
    "committee_memberships": null,
    "community_involvement": null,
    "current_location": "Falun",
    "education": null,
    "family": null,
    "hobbies": null,
    "honorary_titles": null,
    "honors": null,
    "languages_spoken": null,
    "leadership_roles": null,
    "military_service": null,
    "political_positions": null,
    "publications": null,
    "travels": null
}