{
    "career": [
        {
            "position": "attaché",
            "start_year": 1945,
            "organization": "Utrikesdepartementet",
            "location": "Stockholm",
            "country_code": "SWE"
        },
        {
            "position": "Förste sekreterare",
            "start_year": 1955,
            "organization": "Utrikesdepartementet",
            "location": null,
            "country_code": null
        },
        {
            "position": "Direktör",
            "start_year": 1962,
            "organization": "Sveriges Industriförbund",
            "location": null,
            "country_code": null
        }
    ],
    "person": {
        "first_name": "G.",
        "last_name": "Braunerhielm",
        "middle_name": "Erik E",
        "gender": "Male",
        "birth_date": "28-12-1921",
        "birth_place": "Karlskrona",
        "parents": [
            {
                "first_name": "Erik",
                "last_name": "Braunerhielm",
                "gender": "Male",
                "occupation": {
                    "occupation": "kommendör"
                }
            },
            {
                "first_name": "Augusta",
                "last_name": "Ekman",
                "gender": "Female",
                "occupation": null
            }
        ]
    },
    "education": [
        {
            "degree": "Juridisk kandidat",
            "degree_level": "Master's",
            "year": "1945",
            "institution": "Stockholms Universitet"
        }
    ],
    "publications": [
        {
            "title": "Sverige och den gemensamma marknaden",
            "year": "1964",
            "type": "bok"
        }
    ],
    "travels": [
        {
            "country": "New York",
            "country_code": "USA"
        },
        {
            "country": "Washington",
            "country_code": "USA"
        },
        {
            "country": "Ankara",
            "country_code": "TUR"
        },
        {
            "country": "Wien",
            "country_code": "AUT"
        }
    ]
}