{
    "career": [
        {
            "position": "adjunkt",
            "start_year": 1943,
            "organization": "hal Borås",
            "location": "Borås",
            "country_code": null
        },
        {
            "position": "lektor",
            "start_year": 1957,
            "organization": "hal Borås",
            "location": "Borås",
            "country_code": null
        }
    ],
    "person": {
        "first_name": "B",
        "last_name": "Moberg",
        "middle_name": "Ivar",
        "gender": "Male",
        "birth_date": "19-02-1901",
        "birth_place": "Skara",
        "occupation": {
            "occupation": "lektor",
            "occupation_english": "lecturer"
        },
        "parents": [
            {
                "first_name": "Manfred",
                "last_name": "Moberg",
                "middle_name": null,
                "gender": "Male",
                "occupation": {
                    "occupation": "trafikchef och baningenjör",
                    "occupation_english": "traffic manager and railway engineer"
                }
            },
            {
                "first_name": "Maria",
                "last_name": "Granath",
                "middle_name": null,
                "gender": "Female",
                "occupation": null
            }
        ]
    },
    "academic_positions": null,
    "achievements": null,
    "awards": null,
    "board_memberships": [
        {
            "position": "styrelseledamot",
            "organization": "aktiebolag Borås Tidning"
        }
    ],
    "committee_memberships": null,
    "community_involvement": null,
    "current_location": "Borås",
    "education": [
        {
            "degree": "studentexamen",
            "degree_level": "Schooling",
            "year": "1920",
            "institution": "None"
        },
        {
            "degree": "filosofie magister",
            "degree_level": "Master's",
            "year": "1929",
            "institution": "Stockholms Högskola"
        },
        {
            "degree": "filosofie doktor",
            "degree_level": "Doctorate",
            "year": "1938",
            "institution": "None"
        }
    ],
    "family": {
        "spouse": {
            "first_name": "Sigrid",
            "last_name": "Ericson",
            "middle_name": null,
            "gender": "Female",
            "birth_date": null,
            "birth_place": null,
            "occupation": {
                "occupation": "läroverksadjunkt",
                "occupation_english": "teacher at secondary school"
            },
            "parents": [
                {
                    "first_name": "Oscar",
                    "last_name": "Ericson",
                    "middle_name": null,
                    "gender": "Male",
                    "occupation": {
                        "occupation": "köpman",
                        "occupation_english": "merchant"
                    }
                },
                {
                    "first_name": "Selma",
                    "last_name": "Karlsson",
                    "middle_name": null,
                    "gender": "Female",
                    "occupation": null
                }
            ]
        },
        "marriage_year": "1944",
        "divorce_year": null,
        "children": null
    },
    "hobbies": null,
    "honorary_titles": null,
    "honors": null,
    "languages_spoken": null,
    "leadership_roles": null,
    "military_service": null,
    "political_positions": [
        {
            "organization": "Stadsfullmäktige",
            "position": "ledamot",
            "start_year": 1950,
            "end_year": 1962,
            "focus_area": null,
            "significance": null
        }
    ],
    "publications": [
        {
            "title": "Gotland um das Jahr 1700",
            "year": "1938",
            "type": "doktorsavhandling",
            "editions": null,
            "publisher": null,
            "reception": null,
            "signature": null,
            "volumes": null
        },
        {
            "title": "Västergötlands geografi",
            "year": "1950",
            "type": "bok",
            "editions": null,
            "publisher": null,
            "reception": null,
            "signature": null,
            "volumes": "I"
        }
    ],
    "travels": null
}