{
    "career": [
        {
            "position": "ritare o konstruktör",
            "start_year": 1898,
            "organization": "Bofors",
            "location": null,
            "country_code": null
        },
        {
            "position": "ingenjör",
            "start_year": 1899,
            "organization": "Stjärnfors järnverks- o trämassefabrik",
            "location": null,
            "country_code": null
        },
        {
            "position": "ingenjör",
            "start_year": 1901,
            "organization": "Fagersta",
            "location": null,
            "country_code": null
        },
        {
            "position": "överingenjör",
            "start_year": 1903,
            "organization": "Avesta jernverk",
            "location": null,
            "country_code": null
        },
        {
            "position": "styrelseledamot",
            "start_year": 1911,
            "organization": "Lesjöfors",
            "location": null,
            "country_code": null
        },
        {
            "position": "ordförande",
            "start_year": 1911,
            "organization": "Långbans gruvaktiebolag",
            "location": null,
            "country_code": null
        },
        {
            "position": "disponent",
            "start_year": 1913,
            "organization": "Långbans gruvaktiebolag",
            "location": null,
            "country_code": null
        },
        {
            "position": "direktör",
            "start_year": 1922,
            "end_year": 1924,
            "organization": "Wermlands enskilda bank",
            "location": null,
            "country_code": null
        },
        {
            "position": "disponent",
            "start_year": 1926,
            "end_year": 1936,
            "organization": "Carlsdahls aktiebolag",
            "location": null,
            "country_code": null
        },
        {
            "position": "styrelseledamot",
            "start_year": 1939,
            "end_year": 1958,
            "organization": "ett flertal industriella bolag",
            "location": null,
            "country_code": null
        },
        {
            "position": "ledamot",
            "start_year": 1939,
            "end_year": 1958,
            "organization": "riksvärderingsnämnden",
            "location": null,
            "country_code": null
        }
    ],
    "person": {
        "first_name": "N",
        "last_name": "Ericsson",
        "middle_name": "Arvid",
        "gender": "Male",
        "birth_date": "04-08-1876",
        "birth_place": "Karlskoga",
        "occupation": {
            "occupation": "bergsingenjör, före detta disponent",
            "occupation_english": null
        },
        "parents": [
            {
                "first_name": "Anders",
                "last_name": "Ericsson",
                "middle_name": null,
                "gender": "Male",
                "occupation": {
                    "occupation": "bergsbruksidkare",
                    "occupation_english": null
                }
            },
            {
                "first_name": "Charlotta",
                "last_name": "Jansson",
                "middle_name": null,
                "gender": "Female",
                "occupation": null
            }
        ]
    },
    "academic_positions": null,
    "achievements": null,
    "awards": null,
    "board_memberships": null,
    "committee_memberships": null,
    "community_involvement": null,
    "current_location": "Stockholm",
    "education": [
        {
            "degree": "Örebro tekniska elementarskola",
            "degree_level": "Schooling",
            "year": "1892-1895",
            "institution": "Örebro tekniska elementarskola"
        },
        {
            "degree": "Kungliga Tekniska Högskolan",
            "degree_level": "Master's",
            "year": "1898",
            "institution": "Kungliga Tekniska Högskolan"
        }
    ],
    "family": {
        "spouse": {
            "first_name": "Sigrid",
            "last_name": "Fagergren",
            "middle_name": null,
            "gender": "Female",
            "birth_date": null,
            "birth_place": null,
            "occupation": null,
            "parents": [
                {
                    "first_name": "Arved",
                    "last_name": "Fagergren",
                    "middle_name": null,
                    "gender": "Male",
                    "occupation": {
                        "occupation": "godsägare",
                        "occupation_english": null
                    }
                },
                {
                    "first_name": "Hulda",
                    "last_name": "Ajaxson",
                    "middle_name": null,
                    "gender": "Female",
                    "occupation": null
                }
            ]
        },
        "marriage_year": "1905",
        "divorce_year": null,
        "children": null
    },
    "hobbies": null,
    "honorary_titles": null,
    "honors": [
        "Kungliga Vasaorden",
        "Riddare av Nordstjärneorden",
        "Pro Patria sällskaps guldmedalj"
    ],
    "languages_spoken": null,
    "leadership_roles": null,
    "military_service": null,
    "political_positions": null,
    "publications": null,
    "travels": null
}