{
    "career": [
        {
            "position": "Medarbetare",
            "start_year": 1884,
            "end_year": 1905,
            "organization": "Clara Ekströms Optiska Affär",
            "location": "Stockholm",
            "country_code": "SWE"
        },
        {
            "position": "Optiker",
            "start_year": 1905,
            "organization": "Clara Ekströms Optiska Affär",
            "location": "Stockholm",
            "country_code": "SWE"
        },
        {
            "position": "Hovleverantör",
            "start_year": 1905,
            "organization": "Clara Ekströms Optiska Affär",
            "location": "Stockholm",
            "country_code": "SWE"
        },
        {
            "position": "Leverantör",
            "start_year": 1905,
            "organization": "Ett flertal officerare, institutioner",
            "location": "Stockholm",
            "country_code": "SWE"
        }
    ],
    "person": {
        "first_name": "Hilda",
        "last_name": "Tholander",
        "middle_name": "Sofia Elvira",
        "gender": "Female",
        "birth_place": "Stockholm",
        "occupation": {
            "occupation": "Optiker",
            "occupation_english": "Optician"
        }
    },
    "academic_positions": null,
    "achievements": null,
    "awards": null,
    "board_memberships": null,
    "committee_memberships": null,
    "community_involvement": null,
    "current_location": "Stockholm",
    "education": null,
    "family": {
        "spouse": {
            "first_name": "C. G. W.",
            "last_name": "Tholander",
            "gender": "Male",
            "occupation": {
                "occupation": "Optiker",
                "occupation_english": "Optician"
            }
        },
        "marriage_year": "1907",
        "divorce_year": null,
        "children": [
            {
                "first_name": "Carl-Wilhelm",
                "last_name": "Tholander",
                "gender": "Male",
                "birth_year": "1908"
            }
        ]
    },
    "hobbies": null,
    "honorary_titles": null,
    "honors": null,
    "languages_spoken": null,
    "leadership_roles": null,
    "military_service": null,
    "political_positions": null,
    "publications": null,
    "travels": [
        {
            "country": "Tyskland",
            "country_code": "DEU"
        },
        {
            "country": "Frankrike",
            "country_code": "FRA"
        },
        {
            "country": "Belgien",
            "country_code": "BEL"
        },
        {
            "country": "Holland",
            "country_code": "NLD"
        },
        {
            "country": "England",
            "country_code": "GBR"
        },
        {
            "country": "USA",
            "country_code": "USA"
        }
    ]
}