{
    "career": [
        {
            "position": "Rit",
            "start_year": 1912,
            "end_year": 1913,
            "organization": "Elektriska Aktiebolaget Eck",
            "location": "Partille",
            "country_code": null
        },
        {
            "position": "Konstruktör, ritkontorschef och överingenjör",
            "start_year": 1914,
            "end_year": 1927,
            "organization": "Aktiebolaget Svenska Kugghjulsfabriken och SKF",
            "location": null,
            "country_code": null
        },
        {
            "position": "Teknisk chef",
            "start_year": 1928,
            "end_year": null,
            "organization": "Aktiebolaget Svenska Naxos",
            "location": "Lomma",
            "country_code": null
        },
        {
            "position": "Teknisk expert och rådgivare",
            "start_year": 1940,
            "end_year": null,
            "organization": "Aktiebolaget Slipmaterial-Naxos",
            "location": "Västra Värlinge, Lomma och Backarp",
            "country_code": null
        }
    ],
    "person": {
        "first_name": "Axel",
        "last_name": "Löfquist",
        "middle_name": "Fredrik Thure",
        "gender": "Male",
        "birth_date": "18-07-1891",
        "birth_place": "Filipstad",
        "occupation": {
            "occupation": "Civilingenjör",
            "occupation_english": "Civil Engineer"
        },
        "parents": [
            {
                "first_name": "N",
                "last_name": "Löfquist",
                "middle_name": "G",
                "gender": "Male",
                "occupation": {
                    "occupation": "målarmästare",
                    "occupation_english": "master painter"
                }
            },
            {
                "first_name": "Hulda",
                "last_name": "Carlsson",
                "middle_name": null,
                "gender": "Female",
                "occupation": null
            }
        ]
    },
    "academic_positions": null,
    "achievements": null,
    "awards": null,
    "board_memberships": null,
    "committee_memberships": null,
    "community_involvement": null,
    "current_location": "Kungsbacka",
    "education": [
        {
            "degree": "Civilingenjörsexamen",
            "degree_level": "Master's",
            "year": "1912",
            "institution": "Chalmers Tekniska Högskola"
        }
    ],
    "family": {
        "spouse": {
            "first_name": "Fanny",
            "last_name": "Ringblom",
            "middle_name": null,
            "gender": "Female",
            "birth_date": null,
            "birth_place": null,
            "occupation": null,
            "parents": null
        },
        "marriage_year": null,
        "divorce_year": null,
        "children": null
    },
    "hobbies": [
        "Böcker",
        "mässingsljusstakar"
    ],
    "honorary_titles": null,
    "honors": null,
    "languages_spoken": null,
    "leadership_roles": null,
    "military_service": null,
    "political_positions": null,
    "publications": null,
    "travels": [
        {
            "country": "Sydamerika",
            "country_code": "null",
            "year": "1913"
        },
        {
            "country": "Mellanamerika",
            "country_code": "null",
            "year": "1913"
        },
        {
            "country": "Nordafr",
            "country_code": "null",
            "year": "1913"
        },
        {
            "country": "Medelhavsländerna",
            "country_code": "null",
            "year": "1913"
        },
        {
            "country": "Nordamerika",
            "country_code": "null",
            "year": "1925"
        },
        {
            "country": "Nordamerika",
            "country_code": "null",
            "year": "1926"
        },
        {
            "country": "Österrike",
            "country_code": "AUT",
            "year": null
        },
        {
            "country": "Tjeckoslovakien",
            "country_code": "null",
            "year": null
        },
        {
            "country": "Tyskland",
            "country_code": "DEU",
            "year": null
        },
        {
            "country": "Belgien",
            "country_code": "BEL",
            "year": null
        },
        {
            "country": "England",
            "country_code": "GBR",
            "year": null
        }
    ]
}