{
    "career": [
        {
            "position": "Direktör",
            "start_year": 1919,
            "organization": "Werner & Pfleiderer Aktiebolag Stockholm",
            "location": "Stockholm",
            "country_code": "SWE"
        }
    ],
    "person": {
        "first_name": "Carl",
        "last_name": "Gyllensten",
        "middle_name": "Wictor",
        "gender": "Male",
        "birth_date": "13-04-1890",
        "birth_place": "Björneborg, Finland",
        "occupation": {
            "occupation": "Disponent",
            "occupation_english": null
        },
        "parents": [
            {
                "first_name": "J",
                "last_name": "Gyllensten",
                "middle_name": "A W",
                "gender": "Male",
                "occupation": {
                    "occupation": "Pannplåtslagarmästare",
                    "occupation_english": null
                }
            },
            {
                "first_name": "Anna",
                "last_name": "Tilander",
                "middle_name": null,
                "gender": "Female",
                "occupation": null
            }
        ]
    },
    "academic_positions": null,
    "achievements": null,
    "awards": null,
    "board_memberships": null,
    "committee_memberships": null,
    "community_involvement": null,
    "current_location": "Stockholm",
    "education": [
        {
            "degree": "Folkskola",
            "degree_level": "Schooling",
            "year": "None",
            "institution": "None"
        },
        {
            "degree": "Borgarskola",
            "degree_level": "Schooling",
            "year": "None",
            "institution": "None"
        }
    ],
    "family": {
        "spouse": {
            "first_name": "Ingrid",
            "last_name": "Rangström",
            "middle_name": null,
            "gender": "Female",
            "birth_date": null,
            "birth_place": null,
            "occupation": null,
            "parents": null
        },
        "marriage_year": null,
        "divorce_year": null,
        "children": null
    },
    "hobbies": [
        "Bowling",
        "Simning"
    ],
    "honorary_titles": null,
    "honors": null,
    "languages_spoken": null,
    "leadership_roles": null,
    "military_service": null,
    "political_positions": null,
    "publications": null,
    "travels": [
        {
            "country": "Tyskland",
            "country_code": "DEU",
            "year": null
        },
        {
            "country": "Österrike",
            "country_code": "AUT",
            "year": null
        },
        {
            "country": "Ungern",
            "country_code": "HUN",
            "year": null
        },
        {
            "country": "Tjeckoslovakien",
            "country_code": "CZE",
            "year": null
        },
        {
            "country": "Schweiz",
            "country_code": "CHE",
            "year": null
        },
        {
            "country": "Italien",
            "country_code": "ITA",
            "year": null
        },
        {
            "country": "Frankrike",
            "country_code": "FRA",
            "year": null
        },
        {
            "country": "England",
            "country_code": "GBR",
            "year": null
        },
        {
            "country": "Holland",
            "country_code": "NLD",
            "year": null
        },
        {
            "country": "Belgien",
            "country_code": "BEL",
            "year": null
        },
        {
            "country": "Danmark",
            "country_code": "DNK",
            "year": null
        },
        {
            "country": "Norge",
            "country_code": "NOR",
            "year": null
        },
        {
            "country": "Finland",
            "country_code": "FIN",
            "year": null
        },
        {
            "country": "Ryssland",
            "country_code": "RUS",
            "year": null
        }
    ]
}